castellan/__init__.py
castellan/_config_driver.py
castellan/i18n.py
castellan/options.py
castellan/common/__init__.py
castellan/common/exception.py
castellan/common/utils.py
castellan/common/credentials/__init__.py
castellan/common/credentials/credential.py
castellan/common/credentials/keystone_password.py
castellan/common/credentials/keystone_token.py
castellan/common/credentials/password.py
castellan/common/credentials/token.py
castellan/common/objects/__init__.py
castellan/common/objects/certificate.py
castellan/common/objects/key.py
castellan/common/objects/managed_object.py
castellan/common/objects/opaque_data.py
castellan/common/objects/passphrase.py
castellan/common/objects/private_key.py
castellan/common/objects/public_key.py
castellan/common/objects/symmetric_key.py
castellan/common/objects/x_509.py
castellan/key_manager/__init__.py
castellan/key_manager/barbican_key_manager.py
castellan/key_manager/key_manager.py
castellan/key_manager/migration.py
castellan/key_manager/not_implemented_key_manager.py
castellan/key_manager/vault_key_manager.py
castellan/tests/__init__.py
castellan/tests/base.py
castellan/tests/utils.py
castellan/tests/functional/__init__.py
castellan/tests/functional/config.py
castellan/tests/functional/key_manager/__init__.py
castellan/tests/functional/key_manager/test_barbican_key_manager.py
castellan/tests/functional/key_manager/test_key_manager.py
castellan/tests/functional/key_manager/test_vault_key_manager.py
castellan/tests/unit/__init__.py
castellan/tests/unit/test_config_driver.py
castellan/tests/unit/test_options.py
castellan/tests/unit/test_utils.py
castellan/tests/unit/credentials/__init__.py
castellan/tests/unit/credentials/test_keystone_password.py
castellan/tests/unit/credentials/test_keystone_token.py
castellan/tests/unit/credentials/test_password.py
castellan/tests/unit/credentials/test_token.py
castellan/tests/unit/key_manager/__init__.py
castellan/tests/unit/key_manager/fake.py
castellan-5.5.0.dist-info/AUTHORS
castellan-5.5.0.dist-info/LICENSE
castellan-5.5.0.dist-info/METADATA
castellan-5.5.0.dist-info/WHEEL
castellan-5.5.0.dist-info/entry_points.txt
castellan-5.5.0.dist-info/pbr.json
castellan-5.5.0.dist-info/top_level.txt
castellan-5.5.0.dist-info/RECORD
