Metadata-Version: 2.1
Name: castellan
Version: 5.5.0
Summary: Generic Key Manager interface for OpenStack
Author-email: OpenStack <openstack-discuss@lists.openstack.org>
License: Apache-2.0
Project-URL: Homepage, https://docs.openstack.org/castellan/
Project-URL: Repository, https://opendev.org/openstack/castellan/
Classifier: Development Status :: 5 - Production/Stable
Classifier: Environment :: Console
Classifier: Intended Audience :: Developers
Classifier: License :: OSI Approved :: Apache Software License
Classifier: Operating System :: POSIX :: Linux
Classifier: Programming Language :: Python
Classifier: Programming Language :: Python :: 3
Classifier: Programming Language :: Python :: 3.10
Classifier: Programming Language :: Python :: 3.11
Classifier: Programming Language :: Python :: 3.12
Classifier: Programming Language :: Python :: 3.13
Requires-Python: >=3.10
License-File: LICENSE
License-File: AUTHORS
Requires-Dist: pbr >=2.0.0
Requires-Dist: cryptography >=2.7
Requires-Dist: python-barbicanclient >=5.5.0
Requires-Dist: oslo.config >=6.4.0
Requires-Dist: oslo.context >=2.19.2
Requires-Dist: oslo.i18n >=3.15.3
Requires-Dist: oslo.log >=3.36.0
Requires-Dist: oslo.utils >=3.33.0
Requires-Dist: stevedore >=1.20.0
Requires-Dist: keystoneauth1 >=3.4.0
Requires-Dist: requests >=2.18.0
